mcpx/__init__.py
mcpx/py.typed
mcpx/client/transports/docker/__init__.py
mcpx/client/transports/docker/config.py
mcpx/client/transports/docker/docker.py
mcpx-0.1.1.dist-info/METADATA
mcpx-0.1.1.dist-info/WHEEL
mcpx-0.1.1.dist-info/licenses/LICENSE
mcpx-0.1.1.dist-info/RECORD
